cas/cli.py
collaborative_article_sharing-0.1.0.dist-info/LICENSE
collaborative_article_sharing-0.1.0.dist-info/METADATA
collaborative_article_sharing-0.1.0.dist-info/WHEEL
collaborative_article_sharing-0.1.0.dist-info/entry_points.txt
collaborative_article_sharing-0.1.0.dist-info/top_level.txt
collaborative_article_sharing-0.1.0.dist-info/RECORD
