Metadata-Version: 2.1
Name: collaborative-article-sharing
Version: 0.1.0
Summary: Command-line interface for interacting with the CAS API
Author-email: upayan <upayanm3@gmail.com>
License: MIT
Requires-Python: >=3.7
License-File: LICENSE
Requires-Dist: requests
Requires-Dist: sys
Requires-Dist: argparse
